ncloud/__init__.py
ncloud/_version.py
ncloud/completers.py
ncloud/config.py
ncloud/driver.py
ncloud/commands/__init__.py
ncloud/commands/batch.py
ncloud/commands/command.py
ncloud/commands/configure.py
ncloud/commands/dataset.py
ncloud/commands/environment.py
ncloud/commands/group.py
ncloud/commands/interact.py
ncloud/commands/machine.py
ncloud/commands/model.py
ncloud/commands/ncloud_history.py
ncloud/commands/resource.py
ncloud/commands/stats.py
ncloud/commands/stream.py
ncloud/commands/tenant.py
ncloud/commands/token.py
ncloud/commands/user.py
ncloud/commands/util.py
ncloud/commands/volume.py
ncloud/formatting/__init__.py
ncloud/formatting/output.py
ncloud/formatting/time_zone.py
ncloud/util/__init__.py
ncloud/util/arg_processor.py
ncloud/util/compat.py
ncloud/util/file_transfer.py
ncloud/util/make_request.py
ncloud/util/request_processor.py
ncloud/util/sys_commands.py
ncloud/vendor/__init__.py
ncloud/vendor/python/__init__.py
ncloud/vendor/python/argparse.py
ncloud-2.8.1.dist-info/DESCRIPTION.rst
ncloud-2.8.1.dist-info/METADATA
ncloud-2.8.1.dist-info/RECORD
ncloud-2.8.1.dist-info/WHEEL
ncloud-2.8.1.dist-info/entry_points.txt
ncloud-2.8.1.dist-info/metadata.json
ncloud-2.8.1.dist-info/top_level.txt
