Metadata-Version: 2.0
Name: ncloud
Version: 2.8.1
Summary: ncloud is a command line client to help you use and manage Nervana's deep learning cloud.
Home-page: http://www.nervanasys.com
Author: Intel Corporation
Author-email: info@nervanasys.com
License: License :: OSI Approved :: Apache Software License
Platform: UNKNOWN
Classifier: Development Status :: 5 - Production/Stable
Classifier: Environment :: Console
Classifier: Environment :: Console :: Curses
Classifier: Environment :: Web Environment
Classifier: Intended Audience :: End Users/Desktop
Classifier: Intended Audience :: Developers
Classifier: Intended Audience :: Science/Research
Classifier: Operating System :: POSIX
Classifier: Operating System :: MacOS :: MacOS X
Classifier: Operating System :: Microsoft :: Windows
Classifier: Programming Language :: Python
Classifier: Topic :: Scientific/Engineering :: Artificial Intelligence
Classifier: Topic :: Scientific/Engineering :: Information Analysis
Classifier: Topic :: System :: Distributed Computing
Requires-Dist: argcomplete
Requires-Dist: bson
Requires-Dist: conditional
Requires-Dist: configparser
Requires-Dist: future
Requires-Dist: gitpython
Requires-Dist: nauth
Requires-Dist: pip
Requires-Dist: requests
Requires-Dist: tabulate
Requires-Dist: validators
Provides-Extra: secure
Requires-Dist: ndg-httpsclient; extra == 'secure'
Requires-Dist: pyOpenSSL; extra == 'secure'
Requires-Dist: pyasn2; extra == 'secure'
